mypapers/__init__.py
mypapers/config/__init__.py
mypapers/crawl/__init__.py
mypapers/db/__init__.py
mypapers/export/__init__.py
mypapers/plot/__init__.py
mypapers/stats/__init__.py
mypapers/utils/__init__.py
mypapers-0.0.1.dist-info/METADATA
mypapers-0.0.1.dist-info/WHEEL
mypapers-0.0.1.dist-info/top_level.txt
mypapers-0.0.1.dist-info/RECORD
