Metadata-Version: 2.1
Name: mypapers
Version: 0.0.1
Summary: 论文一体化写作神器（Python）
Home-page: https://github.com/MarkShawn2020/mypapers
Author: Mark Shawn
Author-email: shawninjuly@gmail.com
License: UNKNOWN
Platform: UNKNOWN
Classifier: Programming Language :: Python :: 3
Classifier: License :: OSI Approved :: MIT License
Classifier: Operating System :: OS Independent
Requires-Python: >=3.6
